bankingsdk/__init__.py
bankingsdk/bank_client.py
bankingsdk/bank_config.py
bankingsdk/schemas/__init__.py
bankingsdk/schemas/schemas.py
creditsdk-0.1.0.dist-info/METADATA
creditsdk-0.1.0.dist-info/WHEEL
creditsdk-0.1.0.dist-info/top_level.txt
creditsdk-0.1.0.dist-info/RECORD
