Metadata-Version: 2.4
Name: creditsdk
Version: 0.1.0
Summary: Software Development Kit (SDK) client pour l'API Credit Risk
Author-email: N'DOUBA MÔH-ADJONLIN <ndoubajeanclaude@outlook.com>
Classifier: Development Status :: 3 - Alpha
Classifier: Programming Language :: Python :: 3
Classifier: License :: OSI Approved :: MIT License
Classifier: Operating System :: OS Independent
Requires-Python: >=3.11.8
Requires-Dist: httpx>=0.28.1
Requires-Dist: pydantic>=2.11.9
Requires-Dist: backoff>=2.2.1
Requires-Dist: python-dotenv
